menubar/__init__.py
menubar/__main__.py
tests/__init__.py
menubar-0.0.1.dist-info/METADATA
menubar-0.0.1.dist-info/WHEEL
menubar-0.0.1.dist-info/entry_points.txt
menubar-0.0.1.dist-info/top_level.txt
menubar-0.0.1.dist-info/RECORD
